Lab 7/lab7com1.v
//Bradley Trowbridge
//Computer Architecture
//Lab 7
//Component, ALU

module lab7com1 (
    inA,
    inB,
    operation,
    result,
    zero
);

input signed[31:0] inA,inB;
input[3:0] operation;
output signed[31:0]result;
output zero;

wire signed[31:0] inA,inB;
wire[3:0] operation;
reg signed[31:0] result;
reg zero;

always begin
    #1;
  case (operation)
    4'b0000: result = inA + inB;            // A + B
    4'b0001: result = inA - inB;            // A - B
    4'b0010: result = inA & inB;            // A AND B
    4'b0011: result = inA | inB;            // A OR B
    4'b0100: result = inA^inB;              // A XOR B
    4'b0101: result = inA~^inB;             // A NOR B
    4'b0110: result = (((inA < 0) ? -inA : inA) < ((inB < 0) ? -inB : inB)) ? 1 : 0;  // 1 if inA < inB, 0 otherwise (assume unsigned)
    4'b0111: result = inA<<inB;             // Shift inA logically left by inB bits
    4'b1000: result = inA>>inB;             // Shift inA logically right by inB bits
    4'b1001: result = inA>>>inB;            // Shift inA arithmetically right by inB bits
    4'b1010: result = inA;                  // A
    4'b1011: result = ~inA;                 // NOT A
    4'b1100: result = inA+1;                // A + 1
    4'b1101: result = inA-1;                // A - 1
    4'b1110: $display("Not Implemented.");  // not imppl
    4'b1111: $display("Not Implemented.");  // not imppl
    default: $display("Error: Bad operation input.");
  endcase
  zero = !result;
  
end
endmodule

module lab7com1_tb;
    reg signed[31:0] wA,wB;
    reg[3:0] wOperation;
    wire signed[31:0] wResult;
    wire wZero;
    
    reg signed[31:0] rightResult;
    reg rightZero;
    
        reg[100:0] testvectors[0:70];
		reg[7:0] errors;
		reg[7:0] vectornum;
        
initial  begin
    $dumpfile ("lab7com1.vcd"); 
	$dumpvars; 
end

initial begin
	$readmemb("lab7com1_test.txt",testvectors);
	errors = 0;
	vectornum = 0;
end

always begin

	if (testvectors[vectornum] === 101'bXXXX || vectornum === 73) begin    // XXXX is the "End of File" indicator I used
		$display("Test completed with %d errors.", errors);
		$finish;
	end 
	{wA, wB, wOperation, rightResult, rightZero} = testvectors[vectornum];
	#1; 
	if (rightResult != wResult || wZero != rightZero)begin
		errors = errors+1;
		$display("Input %b %b %b incorrectly creates %b %b at line %d.", wA, wB, wOperation, wResult, wZero, vectornum + 2);
    end else begin
	    $display("InA=%b InB=%b Op=%b | Result=%b Zero=%b", wA, wB, wOperation, wResult, wZero);
    end
	vectornum = vectornum +1;
end

lab7com1 uut(
    .inA        (wA),
    .inB        (wB),
    .operation  (wOperation),
    .result     (wResult),
    .zero       (wZero)
);
endmodule

Lab 7/lab7com1.vcd
$date
	Sat Apr 09 22:31:23 2016
$end
$version
	Icarus Verilog
$end
$timescale
	1s
$end
$scope module lab7com1_tb $end
$var wire 1 ! wZero $end
$var wire 32 " wResult [31:0] $end
$var reg 8 # errors [7:0] $end
$var reg 32 $ rightResult [31:0] $end
$var reg 1 % rightZero $end
$var reg 8 & vectornum [7:0] $end
$var reg 32 ' wA [31:0] $end
$var reg 32 ( wB [31:0] $end
$var reg 4 ) wOperation [3:0] $end
$scope module uut $end
$var wire 32 * inA [31:0] $end
$var wire 32 + inB [31:0] $end
$var wire 4 , operation [3:0] $end
$var reg 32 - result [31:0] $end
$var reg 1 ! zero $end
$upscope $end
$upscope $end
$enddefinitions $end
#0
$dumpvars
bx -
b0 ,
b11001100 +
b10101010 *
b0 )
b11001100 (
b10101010 '
b0 &
0%
b101110110 $
b0 #
bx "
x!
$end
#1
b0 '
b0 *
b0 (
b0 +
b0 $
1%
b1 &
0!
b101110110 "
b101110110 -
#2
b11111111111111111111111010100000 '
b11111111111111111111111010100000 *
b101100000 (
b101100000 +
b10 &
1!
b0 "
b0 -
#3
b1111111111111111111111111111111 '
b1111111111111111111111111111111 *
b1 (
b1 +
b10000000000000000000000000000000 $
0%
b11 &
#4
b1010101010101010101010101010101 '
b1010101010101010101010101010101 *
b10101010101010101010101010101010 (
b10101010101010101010101010101010 +
b11111111111111111111111111111111 $
b100 &
0!
b10000000000000000000000000000000 "
b10000000000000000000000000000000 -
#5
b10101010 '
b10101010 *
b11001100 (
b11001100 +
b1 )
b1 ,
b11111111111111111111111111011110 $
b101 &
b11111111111111111111111111111111 "
b11111111111111111111111111111111 -
#6
b11001100 '
b11001100 *
b10101010 (
b10101010 +
b100010 $
b110 &
b11111111111111111111111111011110 "
b11111111111111111111111111011110 -
#7
b11111111111111111111111010100000 '
b11111111111111111111111010100000 *
b11111111111111111111111010100000 (
b11111111111111111111111010100000 +
b0 $
1%
b111 &
b100010 "
b100010 -
#8
b101100000 '
b101100000 *
b1011000000 $
0%
b1000 &
1!
b0 "
b0 -
#9
b10000000000000000000000000000000 '
b10000000000000000000000000000000 *
b1 (
b1 +
b1111111111111111111111111111111 $
b1001 &
0!
b1011000000 "
b1011000000 -
#10
b11111111111111111111111111111111 '
b11111111111111111111111111111111 *
b0 (
b0 +
b10 )
b10 ,
b0 $
1%
b1010 &
b1111111111111111111111111111111 "
b1111111111111111111111111111111 -
#11
b10101010101010101010101010101010 '
b10101010101010101010101010101010 *
b10101010101010101010101010101010 (
b10101010101010101010101010101010 +
b10101010101010101010101010101010 $
0%
b1011 &
1!
b0 "
b0 -
#12
b11111111111111111111111111111111 '
b11111111111111111111111111111111 *
b1111111111111111 (
b1111111111111111 +
b1111111111111111 $
b1100 &
0!
b10101010101010101010101010101010 "
b10101010101010101010101010101010 -
#13
b0 '
b0 *
b0 $
1%
b1101 &
b1111111111111111 "
b1111111111111111 -
#14
b11001100110011001100110011001100 '
b11001100110011001100110011001100 *
b1100110011001100110011001100110 (
b1100110011001100110011001100110 +
b1000100010001000100010001000100 $
0%
b1110 &
1!
b0 "
b0 -
#15
b11111111111111111111111111111111 '
b11111111111111111111111111111111 *
b0 (
b0 +
b11 )
b11 ,
b11111111111111111111111111111111 $
b1111 &
0!
b1000100010001000100010001000100 "
b1000100010001000100010001000100 -
#16
b10101010101010101010101010101010 '
b10101010101010101010101010101010 *
b10101010101010101010101010101010 (
b10101010101010101010101010101010 +
b10101010101010101010101010101010 $
b10000 &
b11111111111111111111111111111111 "
b11111111111111111111111111111111 -
#17
b11111111111111111111111111111111 '
b11111111111111111111111111111111 *
b1111111111111111 (
b1111111111111111 +
b11111111111111111111111111111111 $
b10001 &
b10101010101010101010101010101010 "
b10101010101010101010101010101010 -
#18
b0 '
b0 *
b1111111111111111 $
b10010 &
b11111111111111111111111111111111 "
b11111111111111111111111111111111 -
#19
b11001100110011001100110011001100 '
b11001100110011001100110011001100 *
b1100110011001100110011001100110 (
b1100110011001100110011001100110 +
b11101110111011101110111011101110 $
b10011 &
b1111111111111111 "
b1111111111111111 -
#20
b11111111111111111111111111111111 '
b11111111111111111111111111111111 *
b0 (
b0 +
b100 )
b100 ,
b11111111111111111111111111111111 $
b10100 &
b11101110111011101110111011101110 "
b11101110111011101110111011101110 -
#21
b10101010101010101010101010101010 '
b10101010101010101010101010101010 *
b10101010101010101010101010101010 (
b10101010101010101010101010101010 +
b0 $
1%
b10101 &
b11111111111111111111111111111111 "
b11111111111111111111111111111111 -
#22
b11111111111111111111111111111111 '
b11111111111111111111111111111111 *
b1111111111111111 (
b1111111111111111 +
b11111111111111110000000000000000 $
0%
b10110 &
1!
b0 "
b0 -
#23
b0 '
b0 *
b1111111111111111 $
b10111 &
0!
b11111111111111110000000000000000 "
b11111111111111110000000000000000 -
#24
b11001100110011001100110011001100 '
b11001100110011001100110011001100 *
b1100110011001100110011001100110 (
b1100110011001100110011001100110 +
b10101010101010101010101010101010 $
b11000 &
b1111111111111111 "
b1111111111111111 -
#25
b11111111111111111111111111111111 '
b11111111111111111111111111111111 *
b0 (
b0 +
b101 )
b101 ,
b0 $
1%
b11001 &
b10101010101010101010101010101010 "
b10101010101010101010101010101010 -
#26
b10101010101010101010101010101010 '
b10101010101010101010101010101010 *
b10101010101010101010101010101010 (
b10101010101010101010101010101010 +
b11111111111111111111111111111111 $
0%
b11010 &
1!
b0 "
b0 -
#27
b11111111111111111111111111111111 '
b11111111111111111111111111111111 *
b1111111111111111 (
b1111111111111111 +
b1111111111111111 $
b11011 &
0!
b11111111111111111111111111111111 "
b11111111111111111111111111111111 -
#28
b0 '
b0 *
b11111111111111110000000000000000 $
b11100 &
b1111111111111111 "
b1111111111111111 -
#29
b11001100110011001100110011001100 '
b11001100110011001100110011001100 *
b1100110011001100110011001100110 (
b1100110011001100110011001100110 +
b1010101010101010101010101010101 $
b11101 &
b11111111111111110000000000000000 "
b11111111111111110000000000000000 -
#30
b1 '
b1 *
b1 (
b1 +
b110 )
b110 ,
b0 $
1%
b11110 &
b1010101010101010101010101010101 "
b1010101010101010101010101010101 -
#31
b10000000000000000000000000000001 '
b10000000000000000000000000000001 *
b11111 &
1!
b0 "
b0 -
#32
b1 '
b1 *
b10000000000000000000000000000001 (
b10000000000000000000000000000001 +
b1 $
0%
b100000 &
#33
b111111000000000 '
b111111000000000 *
b111111 (
b111111 +
b0 $
1%
b100001 &
0!
b1 "
b1 -
#34
b111111 '
b111111 *
b111111000000000 (
b111111000000000 +
b1 $
0%
b100010 &
1!
b0 "
b0 -
#35
b11111111111111111111111111111111 '
b11111111111111111111111111111111 *
b11 (
b11 +
b111 )
b111 ,
b11111111111111111111111111111000 $
b100011 &
0!
b1 "
b1 -
#36
b10000000000000000000000000000001 '
b10000000000000000000000000000001 *
b1000 $
b100100 &
b11111111111111111111111111111000 "
b11111111111111111111111111111000 -
#37
b10101010101010101010101010101010 '
b10101010101010101010101010101010 *
b1 (
b1 +
b1010101010101010101010101010100 $
b100101 &
b1000 "
b1000 -
#38
b1010101010101010101010101010101 '
b1010101010101010101010101010101 *
b1111 (
b1111 +
b10101010101010101000000000000000 $
b100110 &
b1010101010101010101010101010100 "
b1010101010101010101010101010100 -
#39
b11001100110011001100110011001100 '
b11001100110011001100110011001100 *
b11111 (
b11111 +
b0 $
1%
b100111 &
b10101010101010101000000000000000 "
b10101010101010101000000000000000 -
#40
b11111111111111111111111111111111 '
b11111111111111111111111111111111 *
b11 (
b11 +
b1000 )
b1000 ,
b11111111111111111111111111111 $
0%
b101000 &
1!
b0 "
b0 -
#41
b10000000000000000000000000000001 '
b10000000000000000000000000000001 *
b10000000000000000000000000000 $
b101001 &
0!
b11111111111111111111111111111 "
b11111111111111111111111111111 -
#42
b10101010101010101010101010101010 '
b10101010101010101010101010101010 *
b1 (
b1 +
b1010101010101010101010101010101 $
b101010 &
b10000000000000000000000000000 "
b10000000000000000000000000000 -
#43
b1010101010101010101010101010101 '
b1010101010101010101010101010101 *
b1111 (
b1111 +
b1010101010101010 $
b101011 &
b1010101010101010101010101010101 "
b1010101010101010101010101010101 -
#44
b11001100110011001100110011001100 '
b11001100110011001100110011001100 *
b11111 (
b11111 +
b1 $
b101100 &
b1010101010101010 "
b1010101010101010 -
#45
b11111111111111111111111111111111 '
b11111111111111111111111111111111 *
b11 (
b11 +
b1001 )
b1001 ,
b11111111111111111111111111111111 $
b101101 &
b1 "
b1 -
#46
b10000000000000000000000000000001 '
b10000000000000000000000000000001 *
b11110000000000000000000000000000 $
b101110 &
b11111111111111111111111111111111 "
b11111111111111111111111111111111 -
#47
b10101010101010101010101010101010 '
b10101010101010101010101010101010 *
b1 (
b1 +
b11010101010101010101010101010101 $
b101111 &
b11110000000000000000000000000000 "
b11110000000000000000000000000000 -
#48
b1010101010101010101010101010101 '
b1010101010101010101010101010101 *
b1111 (
b1111 +
b1010101010101010 $
b110000 &
b11010101010101010101010101010101 "
b11010101010101010101010101010101 -
#49
b11001100110011001100110011001100 '
b11001100110011001100110011001100 *
b11111 (
b11111 +
b11111111111111111111111111111111 $
b110001 &
b1010101010101010 "
b1010101010101010 -
#50
b11111111111111111111111111111111 '
b11111111111111111111111111111111 *
bx (
bx +
b1010 )
b1010 ,
b110010 &
b11111111111111111111111111111111 "
b11111111111111111111111111111111 -
#51
b0 '
b0 *
b0 $
1%
b110011 &
#52
b10101010101010101010101010101010 '
b10101010101010101010101010101010 *
b10101010101010101010101010101010 $
0%
b110100 &
1!
b0 "
b0 -
#53
b1010101010101010101010101010101 '
b1010101010101010101010101010101 *
b1010101010101010101010101010101 $
b110101 &
0!
b10101010101010101010101010101010 "
b10101010101010101010101010101010 -
#54
b11001100110011001100110011001100 '
b11001100110011001100110011001100 *
b11001100110011001100110011001100 $
b110110 &
b1010101010101010101010101010101 "
b1010101010101010101010101010101 -
#55
b11111111111111111111111111111111 '
b11111111111111111111111111111111 *
b1011 )
b1011 ,
b0 $
1%
b110111 &
b11001100110011001100110011001100 "
b11001100110011001100110011001100 -
#56
b0 '
b0 *
b11111111111111111111111111111111 $
0%
b111000 &
1!
b0 "
b0 -
#57
b10101010101010101010101010101010 '
b10101010101010101010101010101010 *
b1010101010101010101010101010101 $
b111001 &
0!
b11111111111111111111111111111111 "
b11111111111111111111111111111111 -
#58
b1010101010101010101010101010101 '
b1010101010101010101010101010101 *
b10101010101010101010101010101010 $
b111010 &
b1010101010101010101010101010101 "
b1010101010101010101010101010101 -
#59
b11001100110011001100110011001100 '
b11001100110011001100110011001100 *
b110011001100110011001100110011 $
b111011 &
b10101010101010101010101010101010 "
b10101010101010101010101010101010 -
#60
b11111111111111111111111111111111 '
b11111111111111111111111111111111 *
b1100 )
b1100 ,
b0 $
1%
b111100 &
b110011001100110011001100110011 "
b110011001100110011001100110011 -
#61
b1111111111111111111111111111111 '
b1111111111111111111111111111111 *
b10000000000000000000000000000000 $
0%
b111101 &
1!
b0 "
b0 -
#62
b11111111111111110000000000000000 '
b11111111111111110000000000000000 *
b11111111111111110000000000000001 $
b111110 &
0!
b10000000000000000000000000000000 "
b10000000000000000000000000000000 -
#63
b1111111111111111 '
b1111111111111111 *
b10000000000000000 $
b111111 &
b11111111111111110000000000000001 "
b11111111111111110000000000000001 -
#64
b11001100110011001100110011001100 '
b11001100110011001100110011001100 *
b11001100110011001100110011001101 $
b1000000 &
b10000000000000000 "
b10000000000000000 -
#65
b11111111111111111111111111111111 '
b11111111111111111111111111111111 *
b1101 )
b1101 ,
b11111111111111111111111111111110 $
b1000001 &
b11001100110011001100110011001101 "
b11001100110011001100110011001101 -
#66
b10000000000000000000000000000000 '
b10000000000000000000000000000000 *
b1111111111111111111111111111111 $
b1000010 &
b11111111111111111111111111111110 "
b11111111111111111111111111111110 -
#67
b11111111111111110000000000000000 '
b11111111111111110000000000000000 *
b11111111111111101111111111111111 $
b1000011 &
b1111111111111111111111111111111 "
b1111111111111111111111111111111 -
#68
b1111111111111111 '
b1111111111111111 *
b1111111111111110 $
b1000100 &
b11111111111111101111111111111111 "
b11111111111111101111111111111111 -
#69
b1 '
b1 *
b0 $
1%
b1000101 &
b1111111111111110 "
b1111111111111110 -
#70
b0 '
b0 *
b0 (
b0 +
b0 )
b0 ,
b0xxx $
x%
b1000110 &
1!
b0 "
b0 -
#71
b1000111 &
