Lab 5/Com 1/lab5com1.v
// Author: Bradley Trowbridge
// Purpose: Lab 5 Computer architecture

//Component 1 – 1 bit 2-to-1 Multiplexor

module lab5com1 (
S,		// one input
D0,		// another input
D1,		// yet another input
Y		// an output
);
//  Input ports
input	S;
input 	D0;
input 	D1;
// Output ports
output Y;

wire S;
wire D0;
wire D1;
wire nS;
wire D0nS;
wire D1S;
wire Y;

not(nS,S);
and (D0nS,D0,nS);
and (D1S,D1,S);
or  (Y,D0nS,D1S);

endmodule

module lab5com1_tb;  // Note, no interface to testbenches
 reg wS,wD0,wD1;      // signals to be commanded must be "reg"
 wire wY;			// output from unit-under-test is "wire"
	reg [3:0] testvectors[0:10]; // the size of the array must match
								 // the number of bits per line, the size of the array should 
								 // meet or exceed the length of the file, warnings are fine.
	reg [7:0] errors;
	reg [7:0] vectornum;
	reg rightY;
 
initial  begin
    $dumpfile ("lab5com1.vcd"); 
	$dumpvars; 
end 

initial begin
	$readmemb("lab5com1test_vec.txt", testvectors); // loads file into an array
	vectornum = 0;
	errors = 0;
end

always // self-checking test bench needs a loop structure that will process lines from a text file
	begin
	
	if (testvectors[vectornum] === 4'bXXXX) begin    // XXXX is the "End of File" indicator I used
		$display("Test completed with %d errors.", errors);
		$finish;
	end
	{wS, wD0, wD1, rightY} = testvectors[vectornum];	
	#1; 
	if (rightY !== wY)
	begin
		errors = errors+1;
		$display("Input %b %b %b incorrectly creates %b.", wS, wD0, wD1, wY);
	end
	$display ("S=%b  D0=%b  D1=%b  Y=%b", wS, wD0, wD1, wY);
	
	vectornum = vectornum+1;
	
	
end

// Connect UUT to test bench signals
lab5com1 uut(
.S	(wS),
.D0	(wD0),
.D1	(wD1),
.Y	(wY)
);
endmodule

Lab 5/Com 1/lab5com1.vcd
$date
	Wed Mar 16 04:07:16 2016
$end
$version
	Icarus Verilog
$end
$timescale
	1s
$end
$scope module lab5com1_tb $end
$var wire 1 ! wY $end
$var reg 8 " errors [7:0] $end
$var reg 1 # rightY $end
$var reg 8 $ vectornum [7:0] $end
$var reg 1 % wD0 $end
$var reg 1 & wD1 $end
$var reg 1 ' wS $end
$scope module uut $end
$var wire 1 % D0 $end
$var wire 1 ( D0nS $end
$var wire 1 & D1 $end
$var wire 1 ) D1S $end
$var wire 1 ' S $end
$var wire 1 ! Y $end
$var wire 1 * nS $end
$upscope $end
$upscope $end
$enddefinitions $end
#0
$dumpvars
1*
0)
0(
0'
0&
0%
b0 $
0#
b0 "
0!
$end
#1
1&
b1 $
#2
1!
1(
1%
0&
1#
b10 $
#3
1&
b11 $
#4
0!
0*
0(
1'
0%
0&
0#
b100 $
#5
1!
1)
1&
1#
b101 $
#6
0!
0)
1%
0&
0#
b110 $
#7
1!
1)
1&
1#
b111 $
#8
b1000 $
